office_to_pdf_client/__init__.py
office_to_pdf_client/_client.py
office_to_pdf_client/_utils.py
office_to_pdf_client-0.1.4.dist-info/METADATA
office_to_pdf_client-0.1.4.dist-info/WHEEL
office_to_pdf_client-0.1.4.dist-info/RECORD
