Metadata-Version: 2.4
Name: office-to-pdf-client
Version: 0.1.4
Summary: Add your description here
Requires-Python: >=3.12
Requires-Dist: httpx[http2]>=0.28.1
